{
    "changeLanguage": "Mudar idioma",
    "homeStat": "Estatísticas",
    "titleScreen": "Início",
    "lastOrder": "Último pedido",
    "titleReview": "Avaliação",
    "updateApp": "Atualizar",
    "seeMore": "Ver mais...",
    "SinceLastMonth": "Desde o mês passado",
    "listOfStatistics": "Lista de estatísticas",
    "allCommands": "Todos os comandos",
    "monday": "Segunda-feira",
    "tuesday": "Terça-feira",
    "wednesday": "Quarta-feira",
    "thursday": "Quinta-feira",
    "friday": "Sexta-feira",
    "saturday": "Sábado",
    "sunday": "Domingo",
    "january": "Janeiro",
    "february": "Fevereiro",
    "march": "Março",
    "april": "Abril",
    "may": "Maio",
    "june": "Junho",
    "july": "Julho",
    "august": "Agosto",
    "september": "Setembro",
    "october": "Outubro",
    "november": "Novembro",
    "december": "Dezembro",
    "titleOrder": "Pedido",
    "total": "Total",
    "alertDeleteOrder": "O cliente e o pedido foram excluídos com sucesso",
    "creditCard": "Cartão de crédito",
    "cash": "Dinheiro",
    "titleSetting": "Configurações",
    "personalization": "Personalização",
    "myRestaurant": "Meu restaurante",
    "cards": "Cartões",
    "hourly": "Por hora",
    "changePassword": "Alterar senha",
    "privacyPolicy": "Política de privacidade",
    "interface": "Interface",
    "clear": "Limpar",
    "themes": "Temas",
    "default": "Padrão",
    "finished": "Finito",
    "prepared_by": "Preparato da",
    "customer_comment": "Commento del cliente",
    "order_summary": "Riepilogo dell'ordine",
    "customer_information": "Informazioni cliente",
    "mars": "Marte",
    "order_ready": "Ordine pronto",
    "order_in_preparation": "Ordine in preparazione",
    "handled": "Preso in carico",
    "units": "Unità",
    "purple": "Roxo",
    "vs_last_year": "vs l'anno scorso",
    "some_clients": "alcuni clienti",
    "turquoiseBlue": "Turquesa azul",
    "textSupport": "Nossa equipe está disponível para responder a todas as suas perguntas de segunda a sexta-feira das 10h às 18h",
    "chatSupport": "Suporte por chat",
    "unpaid": "Não pago",
    "paid": "Pago",
    "productComment": "Comentário do produto",
    "comment": "Comentário",
    "order": "Pedido",
    "menuManagement": "Gerenciamento de cardápio",
    "addProduct": "Adicionar produto",
    "editProduct": "Editar produto",
    "displayAvailableProducts": "Exibir produtos disponíveis",
    "categories": "Categorias",
    "productAvailable": "Produto disponível",
    "userManagement": "Gerenciamento de usuários",
    "addUser": "Adicionar usuário",
    "userList": "Lista de usuários",
    "oldPassword": "Senha antiga",
    "newPassword": "Nova senha",
    "confirmPassword": "Confirmar nova senha",
    "matchPassword": "As senhas não coincidem",
    "validate": "Validar",
    "productName": "Nome do produto",
    "description": "Descrição",
    "category": "Categoria",
    "selectCategory": "Selecionar categoria...",
    "price": "Preço",
    "textImage": "Selecionar imagem",
    "add": "Adicionar",
    "changeImage": "Alterar imagem",
    "delete": "Excluir",
    "editItems": "Editar itens",
    "viewAll": "Ver tudo",
    "addCategory": "Adicionar categoria",
    "listCategory": "Lista de categorias",
    "language": "Idioma",
    "theme": "Tema",
    "support": "Suporte",
    "phone_support": "Suporte telefônico",
    "email_us": "Envie-nos um e-mail",
    "chat_with_us": "Converse conosco",
    "live_chat": "Chat ao vivo",
    "support_hours": "Horário de suporte",
    "support_availability": "Nossa equipe está disponível de segunda a sexta-feira das 9h30 às 18h30",
    "website": "Site",
    "menu": "Cardápio",
    "users": "Usuários",
    "password": "Senha",
    "privacy": "Privacidade",
    "light": "Claro",
    "dark": "Escuro",
    "system": "Sistema",
    "products": "Produtos",
    "assets": "Ativos",
    "general": "Geral",
    "my_restaurant": "Meu restaurante",
    "security": "Segurança",
    "all": "Tudo",
    "delivery": "Entrega",
    "takeaway": "Para viagem",
    "order_history": "Histórico de pedidos",
    "history": "Histórico",
    "vs_last_month": "Comparado ao mês passado",
    "quick_overview": "Visão rápida",
    "monthly_orders": "Pedidos mensais",
    "orders": "Pedidos",
    "best_selling": "Mais vendidos",
    "sales": "Vendas",
    "more_analytics": "Mais análises",
    "revenue": "Receita",
    "performance": "Desempenho",
    "settings": "Configurações",
    "active": "Ativo",
    "greeting": "Olá",
    "home": "Início",
    "best_month": "Melhor mês",
    "largest_order": "Maior pedido",
    "average_basket": "Cesta média",
    "total_orders": "Total de pedidos",
    "this_year": "Este ano",
    "best_selling_products": "Produtos mais vendidos",
    "previous": "Anterior",
    "next": "Próximo",
    "other_statistics": "Outras estatísticas",
    "page": "Página",
    "peak_hour": "Hora de pico",
    "most_active_day": "Dia mais ativo",
    "preferred_mode": "Modo preferido",
    "repurchase_rate": "Taxa de recompra",
    "order_analysis": "Análise de pedidos",
    "total_month": "Total do mês",
    "distribution_for_the_year": "Distribuição para o ano",
    "annual_revenue": "Receita anual",
    "sales_distribution": "Distribuição de vendas",
    "annual": "Anual",
    "best_day": "Melhor dia",
    "best_performance": "Melhor desempenho",
    "monthly_distribution": "Distribuição mensal",
    "other_metrics": "Outras métricas",
    "average_basket_value": "Valor médio da cesta",
    "annual_growth": "Crescimento anual",
    "total_clients": "Total de clientes",
    "loyal_clients": "Clientes fiéis",
    "total_spent": "Total gasto",
    "top_clients": "Principais clientes",
    "spent": "Gasto",
    "new_clients": "Novos clientes",
    "client_metrics": "Métricas de clientes",
    "retention_rate": "Taxa de retenção",
    "average_spending": "Gasto médio",
    "per_client_per_month": "Por cliente por mês",
    "regular_clients": "Clientes regulares",
    "across_all_years": "Ao longo de todos os anos",
    "average_preparation_time": "Tempo médio de preparação",
    "time_by_order_type": "Tempo por tipo de pedido",
    "employee_performance": "Desempenho dos funcionários",
    "on_average": "Em média",
    "peak_hours": "Horas de pico",
    "client_analysis": "Análise de clientes",
    "call": "Ligar",
    "edit": "Editar",
    "first_name": "Nome",
    "last_name": "Sobrenome",
    "email": "E-mail",
    "phone": "Telefone",
    "street": "Rua",
    "city": "Cidade",
    "postal_code": "CEP",
    "country": "País",
    "edit_user": "Editar usuário",
    "type": "Tipo",
    "user_type": "Tipo de usuário",
    "hello": "Olá",
    "Information": "Informazioni",
    "Contact": "Contatto",
    "Phone number": "Numero di telefono",
    "No phone number": "Nessun numero di telefono",
    "Edit phone number": "Modifica numero di telefono",
    "Enter phone number": "Inserisci numero di telefono",
    "Save": "Salva",
    "Delivery": "Consegna",
    "Activate orders": "Attiva ordini",
    "Orders are enabled": "Ordini attivati",
    "Orders are disabled": "Ordini disattivati",
    "Enable orders": "Attiva ordini",
    "Disable orders": "Disattiva ordini",
    "Are you sure you want to enable orders?": "Sei sicuro di voler attivare gli ordini?",
    "Are you sure you want to disable orders? This will prevent new orders from coming in.": "Sei sicuro di voler disattivare gli ordini? Questo impedirà l'arrivo di nuovi ordini.",
    "Pickup orders": "Ordini da asporto",
    "Pickup is enabled": "Asporto attivato",
    "Pickup is disabled": "Asporto disattivato",
    "Enable pickup": "Attiva asporto",
    "Disable pickup": "Disattiva asporto",
    "Are you sure you want to enable pickup orders?": "Sei sicuro di voler attivare gli ordini da asporto?",
    "Are you sure you want to disable pickup orders?": "Sei sicuro di voler disattivare gli ordini da asporto?",
    "Delivery orders": "Ordini a domicilio",
    "Delivery is enabled": "Consegna a domicilio attivata",
    "Delivery is disabled": "Consegna a domicilio disattivata",
    "Enable delivery": "Attiva consegna",
    "Disable delivery": "Disattiva consegna",
    "Are you sure you want to enable delivery orders?": "Sei sicuro di voler attivare le consegne a domicilio?",
    "Are you sure you want to disable delivery orders?": "Sei sicuro di voler disattivare le consegne a domicilio?",
    "Cancel": "Annulla",
    "Confirm": "Conferma",
    "i_am_preparing_this_order": "Sto preparando questo ordine",
    "address": "Indirizzo",
    "estimated_preparation_time": "Tempo di preparazione stimato",
    "back": "Indietro",
    "confirm": "Confermare",
    "in_progress": "In corso",
    "no_product": "Nessun prodotto",
    "confirmation": "Conferma",
    "are_you_sure_order_ready": "Sei sicuro di voler preparare l'ordine?",
    "cancel": "Annulla",
    "print_receipt": "Stampare la ricevuta",
    "updateFeature1": "🌍 Miglioramento della traduzione",
    "updateFeature2": "⏰ Aggiunta dell'orario e della data agli ordini",
    "updateFeature3": "💳 Aggiunto un sistema di pagamento tramite Stripe",
    "updateFeature4": "🖨️ Aggiunta la possibilità di stampare i tuoi scontrini",
    "updateFeature5": "⏳ Gestione personalizzata dei tempi di attesa per un ordine",
    "updateFeature6": "🚚 Gestisci tu stesso i tuoi metodi di consegna",
    "updateFeature7": "🔄 Attiva o disattiva i tuoi ordini",
    "updateFeature8": "⚡ Personalizza il tuo tempo medio di preparazione per avvisare i clienti ed evitare problemi nelle ore di punta",
    "dashboard": "Cruscotto", 
    "add_image": "Aggiungi immagine",
    "menu_details": "Dettagli del menu",
    "menu_name": "Nome del menu",
    "category_name": "Nome della categoria",
    "max_option": "Opzione massima",
    "category_required": "Categoria richiesta",
    "options": "Opzioni",
    "option": "Opzione",
    "option_name": "Nome dell'opzione",
    "extra_price": "Prezzo extra",
    "included_in_menu": "Incluso nel menu",
    "add_option": "Aggiungi opzione",
    "add_category": "Aggiungi categoria",
    "add_menu": "Aggiungi menu",
    "add_a_menu": "Aggiungi un menu",
    "no_option_selected": "Nessuna opzione selezionata",
    "no_category_selected": "Nessuna categoria selezionata",
    "available_menu": "Menu disponibile",
    "edit_menus": "Modifica i menu",
    "menu_list": "Elenco dei menu",
    "new_option": "Nuova opzione",
    "new_category": "Nuova categoria",
    "confirm_deletion": "Conferma eliminazione",
    "no_menu": "Nessun menu",
    "option_deleted_success": "Opzione eliminata con successo",
    "category_deleted_success": "Categoria eliminata con successo",
    "adding_menu_in_progress": "Aggiunta del menu in corso...",
    "menu_updated_success": "Menù modificato con successo",
    "menu_deleted_success": "Menù eliminato con successo",
    "payment_dashboard": "Dashboard di pagamento",
    "lunch_delivery_service": "Servizio di consegna pranzo",
    "dinner_delivery_service": "Servizio di consegna cena",
    "lunch_delivery_disabled": "Consegna pranzo disattivata",
    "dinner_delivery_disabled": "Consegna cena disattivata",
    "max_delivery_distance": "Distanza massima di consegna",
    "kilometers": "chilometri",
    "enable": "Attivare",
    "disable": "Disattivare",
    "confirm_enable_lunch_delivery": "Sei sicuro di voler attivare il servizio di consegna pranzo?",
    "confirm_enable_dinner_delivery": "Sei sicuro di voler attivare il servizio di consegna cena?",
    "confirm_disable_lunch_delivery": "Sei sicuro di voler disattivare il servizio di consegna pranzo?",
    "confirm_disable_dinner_delivery": "Sei sicuro di voler disattivare il servizio di consegna cena?",
    "table": "Tavolo",
    "tables": "Tavoli",
    "table_reservation": "Prenotazione tavolo",
    "reservations": "Prenotazioni",
    "refresh": "Aggiorna",
    "reservation": "Prenotazione",
    "persons": "Persone",
    "person": "Persona",
    "status": "Stato",
    "period": "Periodo",
    "select_period": "Seleziona un periodo",
    "today": "Oggi",
    "tomorrow": "Domani",
    "yesterday": "Ieri",
    "this_week": "Questa settimana",
    "next_week": "Settimana prossima",
    "last_week": "Settimana scorsa",
    "this_month": "Questo mese",
    "next_month": "Mese prossimo",
    "last_month": "Mese scorso",
    "capacity": "Capacità",
    "select_capacity": "Seleziona capacità",
    "select_location": "Seleziona posizione",
    "all": "Tutti",
    "close": "Chiudi",
    "location": "Posizione",
    "select_status": "Seleziona stato",
    "pending": "In attesa",
    "confirmed": "Confermato",
    "canceled": "Annullato",
    "reservation_details": "Dettagli prenotazione",
    "client": "Cliente",
    "date_time": "Data e ora",
    "number_of_persons": "Numero di persone",
    "contact": "Contatto",
    "current_status": "Stato attuale",
    "cancel": "Annulla",
    "table_settings": "Impostazioni tavoli",
    "add_table": "Aggiungi tavolo",
    "table_number": "Numero del tavolo",
    "available": "Disponibile",
    "enable_reservations": "Attiva prenotazioni",
    "disable_reservations": "Disattiva prenotazioni",
    "reservation_enabled": "Prenotazione attivata",
    "reservation_disabled": "Prenotazione disattivata",
    "schedules": "Orari",
    "set_opening_hours": "Configura orari di apertura",
    "lunch": "Pranzo",
    "dinner": "Cena",
    "set_hours_per_day": "Configura gli orari per ogni giorno",
    "day_closed": "Questo giorno è chiuso",
    "new_order": "Nuovo ordine",
    "cancel_order": "Annulla ordine",
    "menu_type": "Tipo di menù",
    "à_la_carte": "Alla carta",
    "all_you_can_eat": "All you can eat",
    "add_products": "Aggiungi prodotti",
    "no_product_in_order": "Nessun prodotto nell'ordine",
    "print_table_number": "Stampa numero tavolo",
    "validate_order": "Conferma ordine",
    "receipt": "Scontrino",
    "menus": "Menù",
    "menu_options": "Opzioni del menù",
    "max": "Max",
    "opening_hours": "Orari di apertura",
    "closed": "Chiuso",
    "add_to_order": "Aggiungi all'ordine",
    "availability": "Disponibilità",
    "show_online": "Mostra online",
    "show_on_site": "Mostra sul posto",
    "configure_menu_type": "Configura i tuoi menù",
    "a_la_carte": "Alla carta",
    "all_you_can_eat_disabled": "All you can eat disattivato",
    "all_you_can_eat_enabled": "All you can eat attivato",
    "a_la_carte_enabled": "Alla carta attivato",
    "a_la_carte_disabled": "Alla carta disattivato",
    "new_menu": "Nuovo menù",
    "edit_menu": "Modifica menù",
    "textPrivacyPolicy1": "Política de Privacidade do YumCo",
    "textPrivacyPolicy2": "Última atualização: 01/01/2025",
    "textPrivacyPolicy3": "A proteção da sua privacidade é muito importante para nós. Esta política de privacidade explica os tipos de informações pessoais relacionadas ao uso do aplicativo móvel YumCo, bem como como essas informações são usadas, armazenadas e protegidas.",
    "textPrivacyPolicy4": "Coleta e uso de informações",
    "textPrivacyPolicy5": "Ao usar o aplicativo móvel YumCo, você fornece informações como seu nome, sobrenome, endereço, endereço de e-mail e número de telefone. Essas informações são coletadas para melhorar sua experiência de usuário e fornecer serviços personalizados. As informações são tratadas de forma confidencial e compartilhadas com terceiros apenas se exigido por lei ou com seu consentimento explícito.",
    "textPrivacyPolicy6": "Proteção das informações",
    "textPrivacyPolicy7": "Implementamos medidas de segurança adequadas para proteger suas informações pessoais contra acesso, modificação, divulgação ou destruição não autorizados. Isso inclui a proteção dos sistemas de computador e a limitação do acesso às informações pessoais apenas aos funcionários necessários.",
    "textPrivacyPolicy8": "Armazenamento das informações",
    "textPrivacyPolicy9": "As informações pessoais coletadas são mantidas pelo período necessário para cumprir os objetivos descritos nesta política de privacidade ou conforme exigido por lei.",
    "textPrivacyPolicy10": "Alterações na política de privacidade",
    "textPrivacyPolicy11": "Reservamo-nos o direito de modificar esta política de privacidade a qualquer momento. Se forem feitas alterações, a política de privacidade atualizada será publicada nesta página com a data de atualização.",
    "textPrivacyPolicy12": "Contato",
    "textPrivacyPolicy13": "Se você tiver dúvidas ou preocupações sobre esta política de privacidade, entre em contato conosco em: contact@yumco.fr",
    "textPrivacyPolicy14": "Ao usar o aplicativo móvel YumCo, você concorda com os termos desta política de privacidade.",
    "minimum_order": "Minimo d'ordine",
    "maximum_distance": "Distanza massima",
    "delivery_zones_conditions": "Zone e condizioni di consegna",
    "add_new_zones_conditions": "Aggiungi nuove zone e condizioni",
    "current_zones_conditions": "Zone e condizioni attuali",
    "configure_zones_conditions": "Configura le tue zone e condizioni"
}